outlinesmlx/__init__.py
outlinesmlx/function.py
outlinesmlx/samplers.py
outlinesmlx-0.0.271.dist-info/LICENSE
outlinesmlx-0.0.271.dist-info/METADATA
outlinesmlx-0.0.271.dist-info/WHEEL
outlinesmlx-0.0.271.dist-info/top_level.txt
outlinesmlx-0.0.271.dist-info/RECORD
